{"rating": 4.0, "review_count": 97, "photos": ["https://s3-media3.fl.yelpcdn.com/bphoto/17PVH9rNTPU2FqbCbaGIxA/o.jpg", "https://s3-media2.fl.yelpcdn.com/bphoto/7uUdvQFItmsoB3jlROZVbw/o.jpg", "https://s3-media2.fl.yelpcdn.com/bphoto/Os4P8G2I1SSvQ6U8Zou4cg/o.jpg"], "url": "https://www.yelp.com/biz/the-elk-in-the-woods-london?adjust_creative=92p07_JjKyriZTQxAXRiKQ&utm_campaign=yelp_api_v3&utm_medium=api_v3_business_lookup&utm_source=92p07_JjKyriZTQxAXRiKQ", "categories": [{"alias": "sandwiches", "title": "Sandwiches"}, {"alias": "breakfast_brunch", "title": "Breakfast & Brunch"}, {"alias": "scandinavian", "title": "Scandinavian"}], "location": {"country": "GB", "city": "London", "address1": "39 Camden Passage", "zip_code": "N1 8EA", "state": "XGL", "address2": "", "address3": ""}, "is_closed": false, "phone": "+442072263535", "term": "restaurants", "hours": [{"hours_type": "REGULAR", "open": [{"start": "0900", "is_overnight": false, "end": "2300", "day": 0}, {"start": "1100", "is_overnight": false, "end": "2300", "day": 1}, {"start": "0900", "is_overnight": false, "end": "2300", "day": 2}, {"start": "0900", "is_overnight": false, "end": "2300", "day": 3}, {"start": "0900", "is_overnight": false, "end": "2300", "day": 4}, {"start": "0900", "is_overnight": false, "end": "2300", "day": 5}, {"start": "0900", "is_overnight": false, "end": "2300", "day": 6}], "is_open_now": false}], "price": "\u00a3\u00a3", "name": "The Elk in the Woods", "coordinates": {"latitude": 51.5352394152221, "longitude": -0.103600895400873}, "is_claimed": true, "id": "the-elk-in-the-woods-london", "image_url": "https://s3-media3.fl.yelpcdn.com/bphoto/17PVH9rNTPU2FqbCbaGIxA/o.jpg"}