{"rating": 5.0, "review_count": 13, "photos": ["https://s3-media2.fl.yelpcdn.com/bphoto/Jo9xRogLu2Gv98dZgp5IEg/o.jpg", "https://s3-media2.fl.yelpcdn.com/bphoto/qGjYR8k5IlDCImgmzKhnLA/o.jpg", "https://s3-media4.fl.yelpcdn.com/bphoto/di7hXrXgw9J-mpHJqByEjQ/o.jpg"], "url": "https://www.yelp.com/biz/ethel-and-andys-sandwich-shop-boston?adjust_creative=92p07_JjKyriZTQxAXRiKQ&utm_campaign=yelp_api_v3&utm_medium=api_v3_business_lookup&utm_source=92p07_JjKyriZTQxAXRiKQ", "location": {"country": "US", "city": "Boston", "address1": "134 K St", "zip_code": "02127", "state": "MA", "address2": "", "address3": ""}, "is_closed": false, "phone": "+16172683027", "term": "restaurants", "categories": [{"title": "Sandwiches", "alias": "sandwiches"}, {"title": "Cheesesteaks", "alias": "cheesesteaks"}, {"title": "Burgers", "alias": "burgers"}], "price": "$", "name": "Ethel and Andy's Sandwich Shop", "coordinates": {"latitude": 42.3382664, "longitude": -71.0373488}, "is_claimed": false, "id": "ethel-and-andys-sandwich-shop-boston", "image_url": "https://s3-media3.fl.yelpcdn.com/bphoto/Jo9xRogLu2Gv98dZgp5IEg/o.jpg"}