{"rating": 4.5, "id": "gravelly-point-park-arlington", "review_count": 167, "photos": ["https://s3-media2.fl.yelpcdn.com/bphoto/b7iGqqi5Px9FQBwA4kcHMA/o.jpg", "https://s3-media3.fl.yelpcdn.com/bphoto/k7sNxqMsrKzyEkEzAEAhuw/o.jpg", "https://s3-media3.fl.yelpcdn.com/bphoto/BJuSI0RjsIAz2IWD2hLoBQ/o.jpg"], "url": "https://www.yelp.com/biz/gravelly-point-park-arlington?adjust_creative=92p07_JjKyriZTQxAXRiKQ&utm_campaign=yelp_api_v3&utm_medium=api_v3_business_lookup&utm_source=92p07_JjKyriZTQxAXRiKQ", "location": {"country": "US", "city": "Arlington", "address1": "George Washington Pkwy", "zip_code": "22202", "state": "VA", "address2": null, "address3": ""}, "is_closed": false, "phone": "", "term": "attractions", "hours": [{"hours_type": "REGULAR", "open": [{"start": "0600", "is_overnight": false, "end": "1800", "day": 0}, {"start": "0600", "is_overnight": false, "end": "1800", "day": 1}, {"start": "0600", "is_overnight": false, "end": "1800", "day": 2}, {"start": "0600", "is_overnight": false, "end": "1800", "day": 3}, {"start": "0600", "is_overnight": false, "end": "1800", "day": 4}, {"start": "0600", "is_overnight": false, "end": "1800", "day": 5}, {"start": "0600", "is_overnight": false, "end": "1800", "day": 6}], "is_open_now": false}], "name": "Gravelly Point Park", "coordinates": {"latitude": 38.8654445903, "longitude": -77.0391317634}, "is_claimed": false, "categories": [{"alias": "parks", "title": "Parks"}], "image_url": "https://s3-media4.fl.yelpcdn.com/bphoto/b7iGqqi5Px9FQBwA4kcHMA/o.jpg"}