{"rating": 2.0, "id": "dominos-pizza-canberra", "review_count": 1, "photos": [], "url": "https://www.yelp.com/biz/dominos-pizza-canberra?adjust_creative=92p07_JjKyriZTQxAXRiKQ&utm_campaign=yelp_api_v3&utm_medium=api_v3_business_lookup&utm_source=92p07_JjKyriZTQxAXRiKQ", "location": {"country": "AU", "city": "Canberra", "address1": "2 Yallourn St", "zip_code": "2601", "state": "ACT", "address2": "", "address3": ""}, "is_closed": false, "phone": "+61262113033", "term": "restaurants", "hours": [{"hours_type": "REGULAR", "open": [{"start": "1100", "is_overnight": false, "end": "2300", "day": 0}, {"start": "1100", "is_overnight": false, "end": "2300", "day": 1}, {"start": "1100", "is_overnight": false, "end": "2300", "day": 2}, {"start": "1100", "is_overnight": false, "end": "2300", "day": 3}, {"start": "1100", "is_overnight": false, "end": "0000", "day": 4}, {"start": "1100", "is_overnight": false, "end": "0000", "day": 5}, {"start": "1100", "is_overnight": false, "end": "2300", "day": 6}], "is_open_now": true}], "name": "Domino's Pizza", "coordinates": {"latitude": -35.2763878253489, "longitude": 149.128136040316}, "is_claimed": false, "categories": [{"alias": "pizza", "title": "Pizza"}], "image_url": ""}