{"rating": 5.0, "id": "boston-boxing-and-fitness-allston", "review_count": 27, "photos": ["https://s3-media1.fl.yelpcdn.com/bphoto/4uYWzsGd_IZB-pHWbkXtpQ/o.jpg"], "url": "https://www.yelp.com/biz/boston-boxing-and-fitness-allston?adjust_creative=92p07_JjKyriZTQxAXRiKQ&utm_campaign=yelp_api_v3&utm_medium=api_v3_business_lookup&utm_source=92p07_JjKyriZTQxAXRiKQ", "location": {"country": "US", "city": "Allston", "address1": "100 Holton St", "zip_code": "02135", "state": "MA", "address2": "", "address3": ""}, "is_closed": false, "phone": "+16179870142", "term": "attractions", "hours": [{"hours_type": "REGULAR", "open": [{"start": "1600", "is_overnight": false, "end": "2200", "day": 0}, {"start": "1600", "is_overnight": false, "end": "2200", "day": 1}, {"start": "1600", "is_overnight": false, "end": "2200", "day": 2}, {"start": "1600", "is_overnight": false, "end": "2200", "day": 3}, {"start": "1600", "is_overnight": false, "end": "2100", "day": 4}, {"start": "1030", "is_overnight": false, "end": "1500", "day": 5}], "is_open_now": false}], "name": "Boston Boxing & Fitness", "coordinates": {"latitude": 42.3603769, "longitude": -71.1381146}, "is_claimed": false, "categories": [{"alias": "gyms", "title": "Gyms"}], "image_url": "https://s3-media4.fl.yelpcdn.com/bphoto/4uYWzsGd_IZB-pHWbkXtpQ/o.jpg"}