{"rating": 4.0, "review_count": 45, "photos": ["https://s3-media4.fl.yelpcdn.com/bphoto/D2UKipHWurgSRG-hw-RBWg/o.jpg", "https://s3-media2.fl.yelpcdn.com/bphoto/DK878APigIngr-p9ykax5g/o.jpg", "https://s3-media3.fl.yelpcdn.com/bphoto/mkB1ROY2W44042rcCraSYw/o.jpg"], "url": "https://www.yelp.com/biz/nexus-art-cafe-manchester?adjust_creative=92p07_JjKyriZTQxAXRiKQ&utm_campaign=yelp_api_v3&utm_medium=api_v3_business_lookup&utm_source=92p07_JjKyriZTQxAXRiKQ", "categories": [{"alias": "musicvenues", "title": "Music Venues"}, {"alias": "coffee", "title": "Coffee & Tea"}, {"alias": "internetcafe", "title": "Internet Cafes"}], "location": {"country": "GB", "city": "Manchester", "address1": "2 Dale Street", "zip_code": "M1 1JW", "state": "XGM", "address2": "", "address3": ""}, "is_closed": false, "phone": "+441612360100", "term": "attractions", "hours": [{"hours_type": "REGULAR", "open": [{"start": "1100", "is_overnight": false, "end": "1830", "day": 0}, {"start": "1100", "is_overnight": false, "end": "1830", "day": 1}, {"start": "1100", "is_overnight": false, "end": "1830", "day": 2}, {"start": "1100", "is_overnight": false, "end": "1830", "day": 3}, {"start": "1100", "is_overnight": false, "end": "1830", "day": 4}, {"start": "1200", "is_overnight": false, "end": "1730", "day": 6}], "is_open_now": false}], "price": "\u00a3", "name": "Nexus Art Cafe", "coordinates": {"latitude": 53.482384240966, "longitude": -2.2355533267624}, "is_claimed": true, "id": "nexus-art-cafe-manchester", "image_url": "https://s3-media4.fl.yelpcdn.com/bphoto/D2UKipHWurgSRG-hw-RBWg/o.jpg"}