{"rating": 3.5, "review_count": 8, "photos": ["https://s3-media1.fl.yelpcdn.com/bphoto/8r4JerHVDbts4e_NPBZ28A/o.jpg", "https://s3-media1.fl.yelpcdn.com/bphoto/dnQGbHJSSdfZzHyfhhULSQ/o.jpg", "https://s3-media3.fl.yelpcdn.com/bphoto/F11q3v3iBzt7sXRGSAWK3A/o.jpg"], "url": "https://www.yelp.com/biz/lorne-hotel-glasgow?adjust_creative=92p07_JjKyriZTQxAXRiKQ&utm_campaign=yelp_api_v3&utm_medium=api_v3_business_lookup&utm_source=92p07_JjKyriZTQxAXRiKQ", "location": {"country": "GB", "address2": "", "address1": "923 Sauchiehall Street", "zip_code": "G3 7TQ", "state": "GLG", "city": "Glasgow", "address3": ""}, "is_closed": false, "phone": "+441413301555", "term": "attractions", "categories": [{"alias": "hotels", "title": "Hotels"}], "price": "\u00a3\u00a3", "name": "Lorne Hotel", "coordinates": {"latitude": 55.8655299, "longitude": -4.2848946}, "is_claimed": false, "id": "lorne-hotel-glasgow", "image_url": "https://s3-media4.fl.yelpcdn.com/bphoto/8r4JerHVDbts4e_NPBZ28A/o.jpg"}