{"rating": 3.0, "review_count": 1, "photos": [], "url": "https://www.yelp.com/biz/norwood-swimming-kensington?adjust_creative=92p07_JjKyriZTQxAXRiKQ&utm_campaign=yelp_api_v3&utm_medium=api_v3_business_lookup&utm_source=92p07_JjKyriZTQxAXRiKQ", "categories": [{"title": "Swimming Pools", "alias": "swimmingpools"}], "is_closed": false, "phone": "+61883664553", "term": "attractions", "hours": [{"hours_type": "REGULAR", "open": [{"start": "0600", "is_overnight": false, "end": "1930", "day": 0}, {"start": "0600", "is_overnight": false, "end": "1930", "day": 1}, {"start": "0600", "is_overnight": false, "end": "1930", "day": 2}, {"start": "0600", "is_overnight": false, "end": "1930", "day": 3}, {"start": "0600", "is_overnight": false, "end": "1930", "day": 4}, {"start": "0800", "is_overnight": false, "end": "1900", "day": 5}, {"start": "0800", "is_overnight": false, "end": "1900", "day": 6}], "is_open_now": false}], "location": {"country": "AU", "address2": null, "address1": "Philips St", "zip_code": "5068", "state": "SA", "city": "Kensington", "address3": null}, "name": "Norwood Swimming", "coordinates": {"latitude": -34.9235274734021, "longitude": 138.641880200954}, "is_claimed": false, "id": "norwood-swimming-kensington", "image_url": ""}