{"rating": 3.5, "review_count": 7, "photos": ["https://s3-media4.fl.yelpcdn.com/bphoto/ZLetYiMAqIPdEWLgFG4gMw/o.jpg", "https://s3-media2.fl.yelpcdn.com/bphoto/E3NcL-O0JJMaVm0K5drPiQ/o.jpg", "https://s3-media2.fl.yelpcdn.com/bphoto/m9L8ucvrlWOVpaDZzix3Ww/o.jpg"], "url": "https://www.yelp.com/biz/oz-turk-pizzas-and-kebabs-sydney?adjust_creative=92p07_JjKyriZTQxAXRiKQ&utm_campaign=yelp_api_v3&utm_medium=api_v3_business_lookup&utm_source=92p07_JjKyriZTQxAXRiKQ", "location": {"country": "AU", "city": "Sydney", "address1": "704 George St", "zip_code": "2000", "state": "NSW", "address2": null, "address3": null}, "is_closed": false, "phone": "+61292801310", "term": "restaurants", "categories": [{"alias": "hotdogs", "title": "Fast Food"}, {"alias": "cafes", "title": "Cafes"}], "price": "$", "name": "Oz Turk Pizza's & Kebabs", "coordinates": {"latitude": -33.8738861, "longitude": 151.2067261}, "is_claimed": false, "id": "oz-turk-pizzas-and-kebabs-sydney", "image_url": "https://s3-media1.fl.yelpcdn.com/bphoto/ZLetYiMAqIPdEWLgFG4gMw/o.jpg"}