{"rating": 3.5, "review_count": 31, "photos": ["https://s3-media2.fl.yelpcdn.com/bphoto/fTCBgYejHltbAWErbInwng/o.jpg", "https://s3-media1.fl.yelpcdn.com/bphoto/U-okMayJNUFO3EauC_wG8g/o.jpg", "https://s3-media1.fl.yelpcdn.com/bphoto/g4pmIRI_wq8eA70S4Fry_Q/o.jpg"], "url": "https://www.yelp.com/biz/sofa-market-san-jose?adjust_creative=92p07_JjKyriZTQxAXRiKQ&utm_campaign=yelp_api_v3&utm_medium=api_v3_business_lookup&utm_source=92p07_JjKyriZTQxAXRiKQ", "categories": [{"title": "Food Court", "alias": "food_court"}], "location": {"country": "US", "city": "San Jose", "address1": "387 S First St", "zip_code": "95113", "state": "CA", "address2": "", "address3": ""}, "is_closed": false, "phone": "+14086425270", "term": "restaurants", "hours": [{"hours_type": "REGULAR", "open": [{"start": "0800", "is_overnight": false, "day": 0, "end": "2200"}, {"start": "0800", "is_overnight": false, "day": 1, "end": "2200"}, {"start": "0800", "is_overnight": false, "day": 2, "end": "2200"}, {"start": "0800", "is_overnight": false, "day": 3, "end": "0000"}, {"start": "0800", "is_overnight": false, "day": 4, "end": "0000"}, {"start": "0900", "is_overnight": false, "day": 5, "end": "0000"}, {"start": "0900", "is_overnight": false, "day": 6, "end": "2200"}], "is_open_now": true}], "price": "$$", "name": "SoFA Market", "coordinates": {"latitude": 37.33017, "longitude": -121.88654}, "is_claimed": true, "id": "sofa-market-san-jose", "image_url": "https://s3-media1.fl.yelpcdn.com/bphoto/fTCBgYejHltbAWErbInwng/o.jpg"}