{"rating": 4.5, "review_count": 3, "photos": ["https://s3-media1.fl.yelpcdn.com/bphoto/AAaqqQwBnoyuMGLWM-brWg/o.jpg", "https://s3-media1.fl.yelpcdn.com/bphoto/SRr3ffKg8lDX-TjSlROnRQ/o.jpg", "https://s3-media4.fl.yelpcdn.com/bphoto/bApsuCpB2Skkni7WPNRHEg/o.jpg"], "url": "https://www.yelp.com/biz/great-space-cafe-melbourne?adjust_creative=92p07_JjKyriZTQxAXRiKQ&utm_campaign=yelp_api_v3&utm_medium=api_v3_business_lookup&utm_source=92p07_JjKyriZTQxAXRiKQ", "categories": [{"title": "Cafes", "alias": "cafes"}], "location": {"country": "AU", "city": "Melbourne", "address1": "Shop 21 Collins Place", "zip_code": "3000", "state": "VIC", "address2": "35 Collins St", "address3": null}, "is_closed": false, "phone": "+61396503065", "term": "restaurants", "hours": [{"hours_type": "REGULAR", "open": [{"start": "0700", "is_overnight": false, "day": 0, "end": "1700"}, {"start": "0700", "is_overnight": false, "day": 1, "end": "1700"}, {"start": "0700", "is_overnight": false, "day": 2, "end": "1700"}, {"start": "0700", "is_overnight": false, "day": 3, "end": "1700"}, {"start": "0700", "is_overnight": false, "day": 4, "end": "1700"}, {"start": "0800", "is_overnight": false, "day": 5, "end": "1600"}, {"start": "0800", "is_overnight": false, "day": 6, "end": "1600"}], "is_open_now": false}], "price": "$$", "name": "Great Space Cafe", "coordinates": {"latitude": -37.8139191, "longitude": 144.9727783}, "is_claimed": false, "id": "great-space-cafe-melbourne", "image_url": "https://s3-media2.fl.yelpcdn.com/bphoto/AAaqqQwBnoyuMGLWM-brWg/o.jpg"}