{"rating": 4.0, "review_count": 13, "photos": ["https://s3-media1.fl.yelpcdn.com/bphoto/eoK8HHLZvsjrFkt0AaVBqg/o.jpg", "https://s3-media3.fl.yelpcdn.com/bphoto/HPBklc7t4YQ3dwT7CnoClQ/o.jpg", "https://s3-media3.fl.yelpcdn.com/bphoto/oF_wG4t52jv_losCRUCyUQ/o.jpg"], "url": "https://www.yelp.com/biz/issus-melbourne?adjust_creative=92p07_JjKyriZTQxAXRiKQ&utm_campaign=yelp_api_v3&utm_medium=api_v3_business_lookup&utm_source=92p07_JjKyriZTQxAXRiKQ", "location": {"country": "AU", "address2": "", "address1": "8-10 Centre Pl", "zip_code": "3000", "state": "VIC", "city": "Melbourne", "address3": ""}, "is_closed": false, "phone": "+61396638844", "term": "restaurants", "categories": [{"alias": "cafes", "title": "Cafes"}, {"alias": "breakfast_brunch", "title": "Breakfast & Brunch"}, {"alias": "modern_european", "title": "Modern European"}], "price": "$$", "name": "Issus", "coordinates": {"latitude": -37.8167114, "longitude": 144.9656372}, "is_claimed": false, "id": "issus-melbourne", "image_url": "https://s3-media2.fl.yelpcdn.com/bphoto/eoK8HHLZvsjrFkt0AaVBqg/o.jpg"}