{"rating": 4.0, "review_count": 92, "photos": ["https://s3-media3.fl.yelpcdn.com/bphoto/pDRM1KFsbLOogbmnDzoEpw/o.jpg", "https://s3-media2.fl.yelpcdn.com/bphoto/02cnQ8zFxrYWQQiDbilsjw/o.jpg", "https://s3-media1.fl.yelpcdn.com/bphoto/sjHLJbw2R-rGGt_ftGCrYA/o.jpg"], "url": "https://www.yelp.com/biz/jinsei-sushi-birmingham?adjust_creative=92p07_JjKyriZTQxAXRiKQ&utm_campaign=yelp_api_v3&utm_medium=api_v3_business_lookup&utm_source=92p07_JjKyriZTQxAXRiKQ", "categories": [{"alias": "sushi", "title": "Sushi Bars"}, {"alias": "japanese", "title": "Japanese"}], "location": {"country": "US", "city": "Birmingham", "address1": "1830 29th St S", "zip_code": "35209", "state": "AL", "address2": "Ste 125", "address3": ""}, "is_closed": false, "phone": "+12058021440", "term": "restaurants", "hours": [{"hours_type": "REGULAR", "open": [{"start": "1700", "is_overnight": false, "end": "2200", "day": 0}, {"start": "1700", "is_overnight": false, "end": "2200", "day": 1}, {"start": "1700", "is_overnight": false, "end": "2200", "day": 2}, {"start": "1700", "is_overnight": false, "end": "2200", "day": 3}, {"start": "1700", "is_overnight": false, "end": "2300", "day": 4}, {"start": "1700", "is_overnight": false, "end": "2300", "day": 5}, {"start": "1700", "is_overnight": false, "end": "2200", "day": 6}], "is_open_now": false}], "price": "$$$", "name": "Jinsei Sushi", "coordinates": {"latitude": 33.479910507787, "longitude": -86.790048747274}, "is_claimed": true, "id": "jinsei-sushi-birmingham", "image_url": "https://s3-media2.fl.yelpcdn.com/bphoto/pDRM1KFsbLOogbmnDzoEpw/o.jpg"}