{"rating": 4.0, "review_count": 18, "photos": ["https://s3-media4.fl.yelpcdn.com/bphoto/iEAQ8jUrOYMW316toYeVkg/o.jpg", "https://s3-media1.fl.yelpcdn.com/bphoto/URhXparXmX8Gz7yDk9u8xg/o.jpg", "https://s3-media3.fl.yelpcdn.com/bphoto/JxV3ybI5hzEg-RPB1Pmd9g/o.jpg"], "url": "https://www.yelp.com/biz/madame-tussauds-blackpool-blackpool?adjust_creative=92p07_JjKyriZTQxAXRiKQ&utm_campaign=yelp_api_v3&utm_medium=api_v3_business_lookup&utm_source=92p07_JjKyriZTQxAXRiKQ", "categories": [{"title": "Museums", "alias": "museums"}, {"title": "Landmarks & Historical Buildings", "alias": "landmarks"}], "is_closed": false, "phone": "+441253625953", "term": "attractions", "hours": [{"hours_type": "REGULAR", "open": [{"start": "1000", "is_overnight": false, "end": "1700", "day": 0}, {"start": "1000", "is_overnight": false, "end": "1700", "day": 1}, {"start": "1000", "is_overnight": false, "end": "1700", "day": 2}, {"start": "1000", "is_overnight": false, "end": "1700", "day": 3}, {"start": "1000", "is_overnight": false, "end": "1700", "day": 4}, {"start": "1000", "is_overnight": false, "end": "1700", "day": 5}, {"start": "1000", "is_overnight": false, "end": "1700", "day": 6}], "is_open_now": false}], "location": {"country": "GB", "address2": null, "address1": "85-89 Promenade", "zip_code": "FY1 5AA", "state": "BPL", "city": "Blackpool", "address3": null}, "name": "Madame Tussauds Blackpool", "coordinates": {"latitude": 53.8117537, "longitude": -3.0544453}, "is_claimed": false, "id": "madame-tussauds-blackpool-blackpool", "image_url": "https://s3-media1.fl.yelpcdn.com/bphoto/iEAQ8jUrOYMW316toYeVkg/o.jpg"}