{"rating": 5.0, "id": "haka-lodge-auckland-auckland", "review_count": 2, "photos": ["https://s3-media2.fl.yelpcdn.com/bphoto/Gs25NH2pfD4nmCSXBSgJKQ/o.jpg", "https://s3-media3.fl.yelpcdn.com/bphoto/7KbifbL21csQyJR66Chbhw/o.jpg"], "url": "https://www.yelp.com/biz/haka-lodge-auckland-auckland?adjust_creative=92p07_JjKyriZTQxAXRiKQ&utm_campaign=yelp_api_v3&utm_medium=api_v3_business_lookup&utm_source=92p07_JjKyriZTQxAXRiKQ", "location": {"country": "NZ", "address2": "", "address1": "373 Karangahape Rd", "zip_code": "1010", "state": "AUK", "city": "Auckland", "address3": null}, "is_closed": false, "name": "Haka Lodge Auckland", "term": "hotels", "phone": "+6493794559", "price": "$", "coordinates": {"latitude": -36.8579, "longitude": 174.75661}, "image_url": "https://s3-media3.fl.yelpcdn.com/bphoto/Gs25NH2pfD4nmCSXBSgJKQ/o.jpg", "categories": [{"title": "Vacation Rentals", "alias": "vacation_rentals"}], "is_claimed": false}