{"rating": 3.0, "review_count": 2, "url": "https://www.yelp.com/biz/jack-pringle-park-auckland?adjust_creative=92p07_JjKyriZTQxAXRiKQ&utm_campaign=yelp_api_v3&utm_medium=api_v3_business_lookup&utm_source=92p07_JjKyriZTQxAXRiKQ", "photos": ["https://s3-media2.fl.yelpcdn.com/bphoto/dqHrH0UgO1pivcU-vn0fjg/o.jpg", "https://s3-media3.fl.yelpcdn.com/bphoto/1eZSlZHEBRy49twhd6w_ow/o.jpg"], "categories": [{"alias": "skate_parks", "title": "Skate Parks"}, {"alias": "playgrounds", "title": "Playgrounds"}], "is_closed": false, "hours": [{"is_open_now": true, "open": [{"start": "0600", "end": "0600", "is_overnight": true, "day": 0}, {"start": "0600", "end": "0600", "is_overnight": true, "day": 1}, {"start": "0600", "end": "0600", "is_overnight": true, "day": 2}, {"start": "0600", "end": "0600", "is_overnight": true, "day": 3}, {"start": "0600", "end": "0600", "is_overnight": true, "day": 4}, {"start": "0600", "end": "0600", "is_overnight": true, "day": 5}, {"start": "0600", "end": "0600", "is_overnight": true, "day": 6}], "hours_type": "REGULAR"}], "name": "Jack Pringle Park", "term": "attractions", "location": {"country": "NZ", "city": "Auckland", "address1": "Pringle Rd", "zip_code": "0610", "state": "AUK", "address2": "Te Atatu Peninsula", "address3": ""}, "phone": "", "coordinates": {"latitude": -36.8419789185983, "longitude": 174.654449116112}, "is_claimed": false, "id": "jack-pringle-park-auckland", "image_url": "https://s3-media3.fl.yelpcdn.com/bphoto/dqHrH0UgO1pivcU-vn0fjg/o.jpg"}