{"rating": 0.0, "id": "mt-albert-lodge-motel-auckland", "review_count": 0, "url": "https://www.yelp.com/biz/mt-albert-lodge-motel-auckland?adjust_creative=92p07_JjKyriZTQxAXRiKQ&utm_campaign=yelp_api_v3&utm_medium=api_v3_business_lookup&utm_source=92p07_JjKyriZTQxAXRiKQ", "photos": [], "location": {"country": "NZ", "address2": null, "address1": "53 Nelson St", "zip_code": "7399", "state": "CAN", "city": "Auckland", "address3": null}, "is_closed": false, "name": "Mt Albert Lodge Motel", "term": "hotels", "phone": "", "coordinates": {"latitude": -36.8485603, "longitude": 174.7594452}, "image_url": "", "categories": [{"title": "Hotels", "alias": "hotels"}], "is_claimed": false}