{"rating": 5.0, "review_count": 185, "photos": ["https://s3-media2.fl.yelpcdn.com/bphoto/E-Zx6Q_rQjvoPzi0b8EVmw/o.jpg", "https://s3-media3.fl.yelpcdn.com/bphoto/CKOauCG7GfUsbn8WOBx4GQ/o.jpg", "https://s3-media3.fl.yelpcdn.com/bphoto/pr2VJ1NU8kCJQFdh55LP_Q/o.jpg"], "url": "https://www.yelp.com/biz/aikopops-denver-3?adjust_creative=92p07_JjKyriZTQxAXRiKQ&utm_campaign=yelp_api_v3&utm_medium=api_v3_business_lookup&utm_source=92p07_JjKyriZTQxAXRiKQ", "categories": [{"title": "Ice Cream & Frozen Yogurt", "alias": "icecream"}, {"title": "Sandwiches", "alias": "sandwiches"}, {"title": "Soup", "alias": "soup"}], "location": {"country": "US", "city": "Denver", "address1": "1284 S Pearl St", "zip_code": "80210", "state": "CO", "address2": null, "address3": ""}, "is_closed": false, "phone": "+13039966400", "term": "restaurants", "hours": [{"hours_type": "REGULAR", "open": [{"start": "1100", "is_overnight": false, "day": 0, "end": "1800"}, {"start": "1100", "is_overnight": false, "day": 1, "end": "1800"}, {"start": "1100", "is_overnight": false, "day": 2, "end": "1800"}, {"start": "1100", "is_overnight": false, "day": 3, "end": "1800"}, {"start": "1100", "is_overnight": false, "day": 4, "end": "1800"}, {"start": "1100", "is_overnight": false, "day": 5, "end": "1800"}, {"start": "1100", "is_overnight": false, "day": 6, "end": "1800"}], "is_open_now": false}], "price": "$", "name": "AikoPops", "coordinates": {"latitude": 39.69321, "longitude": -104.98008}, "is_claimed": true, "id": "aikopops-denver-3", "image_url": "https://s3-media1.fl.yelpcdn.com/bphoto/E-Zx6Q_rQjvoPzi0b8EVmw/o.jpg"}