[{"_id": "58b9d21795d0e024902fd6ef", "pub_date": "2017-03-03T20:29:06+0000", "source": "The New York Times", "type_of_material": "Letter", "section_name": "Opinion", "web_url": "https://www.nytimes.com/2017/03/03/opinion/a-battle-over-the-military-budget.html", "snippet": "Readers oppose a $54 billion increase in the defense budget while cutting funding in other areas....", "document_type": "article", "headline": {"main": "Review: The Boston Symphony\u2019s Radiant Precision", "print_headline": "Savoring an Orchestral Overload"}, "lead_paragraph": "Readers oppose a $54 billion increase in the defense budget while cutting funding in other areas."}]