{"rating": 0.0, "id": "hobart-walking-tours-hobart", "review_count": 0, "photos": ["https://s3-media3.fl.yelpcdn.com/bphoto/Kui801qwXr_PuHNIjg_2WQ/o.jpg", "https://s3-media1.fl.yelpcdn.com/bphoto/LdSDf4hbC2JM-KufN23wtA/o.jpg", "https://s3-media4.fl.yelpcdn.com/bphoto/MwLHnekGzNLPEGxD5WBwJw/o.jpg"], "url": "https://www.yelp.com/biz/hobart-walking-tours-hobart?adjust_creative=92p07_JjKyriZTQxAXRiKQ&utm_campaign=yelp_api_v3&utm_medium=api_v3_business_lookup&utm_source=92p07_JjKyriZTQxAXRiKQ", "location": {"country": "AU", "address2": "", "address1": "", "zip_code": "", "state": "TAS", "city": "Hobart", "address3": ""}, "is_closed": false, "phone": "+61413383207", "term": "hotels", "hours": [{"hours_type": "REGULAR", "open": [{"start": "0900", "is_overnight": false, "end": "1700", "day": 0}, {"start": "0900", "is_overnight": false, "end": "1700", "day": 1}, {"start": "0900", "is_overnight": false, "end": "1700", "day": 2}, {"start": "0900", "is_overnight": false, "end": "2000", "day": 3}, {"start": "0900", "is_overnight": false, "end": "2000", "day": 4}, {"start": "0900", "is_overnight": false, "end": "2000", "day": 5}, {"start": "0900", "is_overnight": false, "end": "1700", "day": 6}], "is_open_now": false}], "name": "Hobart Walking Tours", "coordinates": {"latitude": -42.88164, "longitude": 147.33163}, "is_claimed": true, "categories": [{"alias": "walkingtours", "title": "Walking Tours"}, {"alias": "historicaltours", "title": "Historical Tours"}], "image_url": "https://s3-media2.fl.yelpcdn.com/bphoto/Kui801qwXr_PuHNIjg_2WQ/o.jpg"}