[{"_id": "58b9d3e895d0e024902fd6ff", "pub_date": "2017-03-03T20:36:51+0000", "source": "AP", "type_of_material": "News", "section_name": "U.S.", "web_url": "https://www.nytimes.com/aponline/2017/03/03/us/ap-us-memphis-police-review-the-latest.html", "snippet": "The Latest on the Justice Department's decision to halt a review of the Memphis Police Department (all times local):...", "document_type": "article", "headline": {"kicker": "Trilobites", "main": "How the Amazon\u2019s Cashews and Cacao Point to Cultivation by the Ancients", "print_headline": "How the Amazon\u2019s Cashews and Cacao Point to Cultivation by the Ancients", "content_kicker": "Trilobites"}, "lead_paragraph": "The Latest on the Justice Department's decision to halt a review of the Memphis Police Department (all times local):"}]