[{"_id": "58b9b0a995d0e024902fd682", "pub_date": "2017-03-03T18:06:29+0000", "source": "Reuters", "type_of_material": "News", "section_name": "Business Day", "web_url": "https://www.nytimes.com/reuters/2017/03/03/business/03reuters-usa-fed-yellen.html", "snippet": "The U.S. Federal Reserve's long-stalled 'liftoff' of interest rates may finally get airborne this year as policymakers from Chair Janet Yellen on Friday to regional leaders across the United States signaled that the era of easy money is drawing to...", "document_type": "article", "headline": {"main": "FIFA Chief 'Confident' of Video Officials at World Cup", "print_headline": "FIFA Chief 'Confident' of Video Officials at World Cup"}, "lead_paragraph": "The U.S. Federal Reserve's long-stalled 'liftoff' of interest rates may finally get airborne this year as policymakers from Chair Janet Yellen on Friday to regional leaders across the United States signaled that the era of easy money is drawing to a close."}]