[{"_id": "58b9932a95d0e024902fd611", "pub_date": "2017-03-03T16:00:30+0000", "source": "Reuters", "type_of_material": "News", "section_name": "Business Day", "web_url": "https://www.nytimes.com/reuters/2017/03/03/business/03reuters-audi-recall.html", "snippet": "Volkswagen's luxury division Audi is recalling 681,000 cars in China to fix coolant pumps that could overheat, a spokesman said....", "document_type": "article", "headline": {"main": "Walls, Drones and Mines: Turkey Tightens Border as Syria Incursion Deepens", "print_headline": "Walls, Drones and Mines: Turkey Tightens Border as Syria Incursion Deepens"}, "lead_paragraph": "Volkswagen's luxury division Audi is recalling 681,000 cars in China to fix coolant pumps that could overheat, a spokesman said."}]