[{"_id": "58b987f495d0e024902fd5ed", "pub_date": "2017-03-03T15:12:47+0000", "source": "AP", "type_of_material": "News", "section_name": "U.S.", "web_url": "https://www.nytimes.com/aponline/2017/03/03/us/politics/ap-us-economy-services.html", "snippet": "U.S. services companies expanded in February at the fastest pace since October 2015....", "document_type": "article", "headline": {"kicker": "Fashion Review", "main": "Rituals, Wild Animals and a Few Giggles", "print_headline": "High Priestesses of the Runway Wild", "content_kicker": "Fashion Review"}, "lead_paragraph": "U.S. services companies expanded in February at the fastest pace since October 2015."}]