[{"_id": "58b9de2b95d0e024902fd729", "pub_date": "2017-03-03T21:20:38+0000", "source": "The New York Times", "type_of_material": "News", "section_name": "Business Day", "web_url": "https://www.nytimes.com/2017/03/03/business/retirement/working-longer-may-benefit-your-health.html", "snippet": "Though the science is inconclusive, anecdotal evidence finds benefits from continuing to work past the traditional retirement age....", "document_type": "article", "headline": {"main": "Costco and Revlon Slump; Big Lots and KeyCorp Advance", "print_headline": "Costco and Revlon Slump; Big Lots and KeyCorp Advance"}, "lead_paragraph": "Though the science is inconclusive, anecdotal evidence finds benefits from continuing to work past the traditional retirement age."}]