[{"_id": "58bac50795d0e024902fd852", "pub_date": "2017-03-04T13:45:36+0000", "source": "AP", "type_of_material": "News", "section_name": "World", "web_url": "https://www.nytimes.com/aponline/2017/03/04/world/europe/ap-eu-rel-vatican-finances.html", "snippet": "The Vatican has issued new figures showing it narrowed its deficit by half in 2015 to 12.4 million euros ($13 million)....", "document_type": "article", "headline": {"main": "Ethiopia Opposition Leader Charged With Inciting Unrest", "print_headline": "Ethiopia Opposition Leader Charged With Inciting Unrest"}, "lead_paragraph": "The Vatican has issued new figures showing it narrowed its deficit by half in 2015 to 12.4 million euros ($13 million)."}]