[{"_id": "58baa8e295d0e024902fd836", "pub_date": "2017-03-04T11:45:30+0000", "source": "Reuters", "type_of_material": "News", "section_name": "Business Day", "web_url": "https://www.nytimes.com/reuters/2017/03/04/business/04reuters-opel-m-a-psa-pc.html", "snippet": "General Motors and France's PSA Group will hold a press conference on Monday morning, they said on Saturday, with the subject expected to be the acquisition of the U.S. carmaker's loss-making Opel unit....", "document_type": "article", "headline": {"main": "Libya's NOC Reviewed Loading Schedules After Clashes Near Oil Ports", "print_headline": "Libya's NOC Reviewed Loading Schedules After Clashes Near Oil Ports"}, "lead_paragraph": "General Motors and France's PSA Group will hold a press conference on Monday morning, they said on Saturday, with the subject expected to be the acquisition of the U.S. carmaker's loss-making Opel unit."}]