[{"_id": "58ba4a0b95d0e024902fd7e8", "pub_date": "2017-03-04T05:00:52+0000", "source": "AP", "type_of_material": "News", "section_name": "Sports", "web_url": "https://www.nytimes.com/aponline/2017/03/04/sports/basketball/ap-bkn-thunder-suns.html", "snippet": "Phoenix native Alan Williams walked up the court with a few seconds left and looked over at the broadcast table, a victory in hand for his Suns....", "document_type": "article", "headline": {"main": "Jeanie Buss, Fearing Brothers\u2019 Takeover of Lakers, Briefly Takes to Court", "print_headline": "Pro Basketball; The Buss Family Takes It to Court"}, "lead_paragraph": "Phoenix native Alan Williams walked up the court with a few seconds left and looked over at the broadcast table, a victory in hand for his Suns."}]