[{"_id": "58ba2bd395d0e024902fd7c3", "pub_date": "2017-03-04T02:51:46+0000", "source": "AP", "type_of_material": "News", "section_name": "Sports", "web_url": "https://www.nytimes.com/aponline/2017/03/03/sports/hockey/ap-hkn-lightning-penguins.html", "snippet": "Mark Streit was dealt from Philadelphia to Tampa Bay to Pittsburgh in the span of a few hours at the trade deadline on Wednesday....", "document_type": "article", "headline": {"main": "DeRozan, Powell Lead Raptors Past Wizards 114-106", "print_headline": "DeRozan, Powell Lead Raptors Past Wizards 114-106"}, "lead_paragraph": "Mark Streit was dealt from Philadelphia to Tampa Bay to Pittsburgh in the span of a few hours at the trade deadline on Wednesday."}]