[{"_id": "58bd8f6095d0e024902fdc97", "pub_date": "2017-03-06T16:33:28+0000", "source": "Reuters", "type_of_material": "News", "section_name": "Business Day", "web_url": "https://www.nytimes.com/reuters/2017/03/06/business/06reuters-saudi-aramco.html", "snippet": "Saudi Aramco's listing process is going as planned, and is expected to take place in the second half of 2018, Chief Executive Amin Nasser said on Monday....", "document_type": "article", "headline": {"main": "Senate to Consider Repeal of Obama-Era Labor Rule", "print_headline": "Senate to Consider Repeal of Obama-Era Labor Rule"}, "lead_paragraph": "Saudi Aramco's listing process is going as planned, and is expected to take place in the second half of 2018, Chief Executive Amin Nasser said on Monday. "}]