[{"_id": "58bd356595d0e024902fdbab", "pub_date": "2017-03-06T10:09:35+0000", "source": "Reuters", "type_of_material": "News", "section_name": "Sports", "web_url": "https://www.nytimes.com/reuters/2017/03/06/sports/soccer/06reuters-soccer-england-mun-mourinho.html", "snippet": "Manchester United manager Jose Mourinho is concerned that his side's inability to win home games may cost them a Champions League qualification spot this season....", "document_type": "article", "headline": {"main": "Greek Economy Slumps in Fourth Quarter, Hurt by Net Exports", "print_headline": "Greek Economy Slumps in Fourth Quarter, Hurt by Net Exports"}, "lead_paragraph": "Manchester United manager Jose Mourinho is concerned that his side's inability to win home games may cost them a Champions League qualification spot this season."}]