{"rating": 4.5, "review_count": 65, "photos": ["https://s3-media4.fl.yelpcdn.com/bphoto/gQ_mp8werfQcnDd_7DW2eg/o.jpg", "https://s3-media2.fl.yelpcdn.com/bphoto/L8lwG8Bywiw55hv9yL9Vig/o.jpg", "https://s3-media1.fl.yelpcdn.com/bphoto/DVQjQdXdbTPWweoyt6yXlw/o.jpg"], "url": "https://www.yelp.com/biz/inner-strength-studios-watertown?adjust_creative=92p07_JjKyriZTQxAXRiKQ&utm_campaign=yelp_api_v3&utm_medium=api_v3_business_lookup&utm_source=92p07_JjKyriZTQxAXRiKQ", "categories": [{"alias": "yoga", "title": "Yoga"}], "location": {"country": "US", "city": "Watertown", "address1": "309 Main St", "zip_code": "02472", "state": "MA", "address2": "", "address3": ""}, "is_closed": false, "phone": "+16179240111", "term": "attractions", "hours": [{"hours_type": "REGULAR", "open": [{"start": "0600", "is_overnight": false, "end": "2045", "day": 0}, {"start": "0600", "is_overnight": false, "end": "2000", "day": 1}, {"start": "0530", "is_overnight": false, "end": "2045", "day": 2}, {"start": "0600", "is_overnight": false, "end": "2000", "day": 3}, {"start": "0600", "is_overnight": false, "end": "1930", "day": 4}, {"start": "0630", "is_overnight": false, "end": "1800", "day": 5}, {"start": "0630", "is_overnight": false, "end": "1800", "day": 6}], "is_open_now": false}], "price": "$$", "name": "Inner Strength Studios", "coordinates": {"latitude": 42.37006, "longitude": -71.19038}, "is_claimed": true, "id": "inner-strength-studios-watertown", "image_url": "https://s3-media2.fl.yelpcdn.com/bphoto/gQ_mp8werfQcnDd_7DW2eg/o.jpg"}