{"rating": 4.0, "review_count": 295, "photos": ["https://s3-media4.fl.yelpcdn.com/bphoto/cTOIJbqSbYQ-kyqiw2MiLw/o.jpg", "https://s3-media1.fl.yelpcdn.com/bphoto/PiFpXPUiRrP-NOgRHL28rg/o.jpg", "https://s3-media1.fl.yelpcdn.com/bphoto/91squkfMxY4-1PB05XInzw/o.jpg"], "url": "https://www.yelp.com/biz/shanghai-lounge-washington?adjust_creative=92p07_JjKyriZTQxAXRiKQ&utm_campaign=yelp_api_v3&utm_medium=api_v3_business_lookup&utm_source=92p07_JjKyriZTQxAXRiKQ", "categories": [{"title": "Chinese", "alias": "chinese"}, {"title": "Asian Fusion", "alias": "asianfusion"}, {"title": "Cocktail Bars", "alias": "cocktailbars"}], "location": {"country": "US", "address2": "", "address1": "1734 Wisconsin Ave NW", "zip_code": "20007", "state": "DC", "city": "Washington", "address3": ""}, "is_closed": false, "phone": "+12023381588", "term": "restaurants", "hours": [{"hours_type": "REGULAR", "open": [{"start": "1100", "is_overnight": false, "end": "2230", "day": 0}, {"start": "1100", "is_overnight": false, "end": "2230", "day": 1}, {"start": "1100", "is_overnight": false, "end": "2230", "day": 2}, {"start": "1100", "is_overnight": false, "end": "2230", "day": 3}, {"start": "1100", "is_overnight": false, "end": "2300", "day": 4}, {"start": "1100", "is_overnight": false, "end": "2300", "day": 5}, {"start": "1130", "is_overnight": false, "end": "2200", "day": 6}], "is_open_now": false}], "price": "$$", "name": "Shanghai Lounge", "coordinates": {"latitude": 38.914586, "longitude": -77.067402}, "is_claimed": true, "id": "shanghai-lounge-washington", "image_url": "https://s3-media1.fl.yelpcdn.com/bphoto/cTOIJbqSbYQ-kyqiw2MiLw/o.jpg"}