{"rating": 4.0, "review_count": 4, "photos": ["https://s3-media1.fl.yelpcdn.com/bphoto/Tu-kmpovy705nZl6_SE1tw/o.jpg", "https://s3-media3.fl.yelpcdn.com/bphoto/_wnHoKCgkuQdf-slU-V_sA/o.jpg", "https://s3-media2.fl.yelpcdn.com/bphoto/Y_rw3CSCmt-a9gVwCPezJg/o.jpg"], "url": "https://www.yelp.com/biz/38-espresso-kingston?adjust_creative=92p07_JjKyriZTQxAXRiKQ&utm_campaign=yelp_api_v3&utm_medium=api_v3_business_lookup&utm_source=92p07_JjKyriZTQxAXRiKQ", "categories": [{"alias": "cafes", "title": "Cafes"}], "location": {"country": "AU", "city": "Kingston", "address1": "Lot 2", "zip_code": "2604", "state": "ACT", "address2": "Trevillian Quay", "address3": ""}, "is_closed": false, "phone": "+61261626027", "term": "restaurants", "hours": [{"hours_type": "REGULAR", "open": [{"start": "0700", "is_overnight": false, "end": "1500", "day": 0}, {"start": "0700", "is_overnight": false, "end": "1500", "day": 1}, {"start": "0700", "is_overnight": false, "end": "1500", "day": 2}, {"start": "0700", "is_overnight": false, "end": "1500", "day": 3}, {"start": "0700", "is_overnight": false, "end": "1500", "day": 4}, {"start": "0700", "is_overnight": false, "end": "1500", "day": 5}, {"start": "0800", "is_overnight": false, "end": "1500", "day": 6}], "is_open_now": false}], "price": "$", "name": "38 Espresso", "coordinates": {"latitude": -35.3111321327978, "longitude": 149.145896760848}, "is_claimed": false, "id": "38-espresso-kingston", "image_url": "https://s3-media2.fl.yelpcdn.com/bphoto/Tu-kmpovy705nZl6_SE1tw/o.jpg"}