[{"web_url": "https://www.nytimes.com/slideshow/2017/03/03/realestate/on-the-market-in-new-york-city.html", "source": "The New York Times", "_id": "58b9d58b95d0e024902fd702", "pub_date": "2017-03-03T20:43:48+0000", "lead_paragraph": "This week\u2019s properties are on the Upper East Side, in Murray Hill and in Fort Greene, Brooklyn.", "section_name": "Real Estate", "type_of_material": "Slideshow", "snippet": "This week\u2019s properties are on the Upper East Side, in Murray Hill and in Fort Greene, Brooklyn....", "document_type": "multimedia", "headline": {"print_headline": "How the Amazon\u2019s Cashews and Cacao Point to Cultivation by the Ancients", "main": "How the Amazon\u2019s Cashews and Cacao Point to Cultivation by the Ancients", "kicker": "Trilobites", "content_kicker": "Trilobites"}}]