[{"web_url": "https://www.nytimes.com/2017/03/03/arts/music/popcast-future-migos-atlanta-hip-hop.html", "source": "The New York Times", "_id": "58b9bfc195d0e024902fd6b5", "pub_date": "2017-03-03T19:10:51+0000", "lead_paragraph": "Rappers from Atlanta are dominating pop music this year. A panel discusses Migos, Lil Yachty and more of the city\u2019s budding stars on Popcast.", "section_name": "Arts", "type_of_material": "News", "snippet": "Rappers from Atlanta are dominating pop music this year. A panel discusses Migos, Lil Yachty and more of the city\u2019s budding stars on Popcast....", "document_type": "article", "headline": {"main": "How to Read Proust in the Original", "print_headline": "How to Read Proust in the Original"}}]