[{"web_url": "https://www.nytimes.com/aponline/2017/03/04/sports/ncaabasketball/ap-bkc-t25-florida-vanderbilt.html", "source": "AP", "_id": "58bb2ff095d0e024902fd8f6", "pub_date": "2017-03-04T21:21:43+0000", "lead_paragraph": "First-year coach Bryce Drew believes his Vanderbilt Commodores have put together a very strong resume for the NCAA Tournament.", "section_name": "Sports", "type_of_material": "News", "snippet": "First-year coach Bryce Drew believes his Vanderbilt Commodores have put together a very strong resume for the NCAA Tournament....", "document_type": "article", "headline": {"print_headline": "The Declining Fortunes of Women at The Times", "main": "The Declining Fortunes of Women at The Times", "kicker": "The Public Editor", "content_kicker": "The Public Editor"}}]