[{"web_url": "https://www.nytimes.com/2017/03/04/us/migrants-facing-old-deportation-orders.html", "source": "The New York Times", "_id": "58bb040695d0e024902fd8b8", "pub_date": "2017-03-04T18:14:20+0000", "lead_paragraph": "Unauthorized immigrants who have stayed in the United States after being ordered deported have emerged as an easy target of the Trump administration\u2019s aims.", "section_name": "U.S.", "type_of_material": "News", "snippet": "Unauthorized immigrants who have stayed in the United States after being ordered deported have emerged as an easy target of the Trump administration\u2019s aims....", "document_type": "article", "headline": {"main": "Poland Wants Center-Right MEP to Replace Tusk as European Council Head", "print_headline": "Poland Wants Center-Right MEP to Replace Tusk as European Council Head"}}]