[{"web_url": "https://www.nytimes.com/2017/03/05/arts/design/coming-to-the-met-roof-a-young-sculptors-scavenger-hunt.html", "source": "The New York Times", "_id": "58bc8bf795d0e024902fda89", "pub_date": "2017-03-05T22:06:38+0000", "lead_paragraph": "Adri\u00e1n Villar Rojas will use pieces from the Metropolitan Museum of Art\u2019s collection as inspiration for large-scale sculptures.", "section_name": "Arts", "type_of_material": "News", "snippet": "Adri\u00e1n Villar Rojas will use pieces from the Metropolitan Museum of Art\u2019s collection as inspiration for large-scale sculptures....", "document_type": "article", "headline": {"main": "How Liberian Women Delivered Africa\u2019s First Female President", "print_headline": "How Women Delivered Africa\u2019s First Female President"}}]