[{"web_url": "https://www.nytimes.com/aponline/2017/03/05/us/ap-us-insider-qa-ahv-communities.html", "source": "AP", "_id": "58bc1ac495d0e024902fd9fa", "pub_date": "2017-03-05T14:03:39+0000", "lead_paragraph": "Whether it's would-be homebuyers frustrated by rising U.S. home prices or renters eager for an alternative to cramped apartment living, many are increasingly opting to rent a house.", "section_name": "U.S.", "type_of_material": "News", "snippet": "Whether it's would-be homebuyers frustrated by rising U.S. home prices or renters eager for an alternative to cramped apartment living, many are increasingly opting to rent a house....", "document_type": "article", "headline": {"main": "Notable Career Ends With Sentencing in United Airlines Case", "print_headline": "Notable Career Ends With Sentencing in United Airlines Case"}}]