[{"web_url": "https://www.nytimes.com/aponline/2017/03/06/us/ap-us-father-slain.html", "source": "AP", "_id": "58bd653195d0e024902fdc19", "pub_date": "2017-03-06T13:33:33+0000", "lead_paragraph": "Police say a 19-year-old Maryland man is charged with fatally shooting his father at their home.", "section_name": "U.S.", "type_of_material": "News", "snippet": "Police say a 19-year-old Maryland man is charged with fatally shooting his father at their home....", "document_type": "article", "headline": {"print_headline": "Minding the Gaps", "main": "In David Shields\u2019s Brief Essays, People May Be Farther Than They Appear", "kicker": "Nonfiction", "content_kicker": "Nonfiction"}}]